converter/__init__.py
converter/dbt_metrics_to_semantic_model_converter.py
converter/main.py
converter/spec_upgrade.py
metricflow_parsing/__init__.py
metricflow_parsing/dbt_dir_to_model.py
metricflow_parsing/dbt_to_metricflow.py
dbt_metrics_converter-0.1.5.3.dist-info/METADATA
dbt_metrics_converter-0.1.5.3.dist-info/WHEEL
dbt_metrics_converter-0.1.5.3.dist-info/entry_points.txt
dbt_metrics_converter-0.1.5.3.dist-info/RECORD
