Metadata-Version: 2.1
Name: dbt-metrics-converter
Version: 0.1.5.3
Summary: Easily convert an out of date dbt metrics spec into the latest suported metrics spec in dbt
Author: Jordan Stein
Author-email: jordan.stein77@gmail.com
Requires-Python: >=3.8,<3.10
Classifier: Programming Language :: Python :: 3
Classifier: Programming Language :: Python :: 3.8
Classifier: Programming Language :: Python :: 3.9
Requires-Dist: click (>=8.1.3,<9.0.0)
Requires-Dist: dbt-core (>=1.5.0,<2.0.0)
Requires-Dist: dbt-semantic-interfaces (>=0.1.0.dev4,<0.2.0)
Requires-Dist: metricflow (==0.200.0.dev4)
